poetry_plugin_tweak_dependencies_version/__init__.py
poetry_plugin_tweak_dependencies_version/py.typed
poetry_plugin_tweak_dependencies_version-1.5.5.dist-info/LICENSE
poetry_plugin_tweak_dependencies_version-1.5.5.dist-info/METADATA
poetry_plugin_tweak_dependencies_version-1.5.5.dist-info/WHEEL
poetry_plugin_tweak_dependencies_version-1.5.5.dist-info/entry_points.txt
poetry_plugin_tweak_dependencies_version-1.5.5.dist-info/RECORD
