Metadata-Version: 2.3
Name: poetry-plugin-tweak-dependencies-version
Version: 1.5.5
Summary: Poetry plugin used to tweak dependency versions
License: BSD-2-Clause
Keywords: poetry,plugin,version,versioning,dynamic
Author: Stéphane Brunner
Author-email: stephane.brunner@camptocamp.com
Requires-Python: >=3.10
Classifier: Development Status :: 4 - Beta
Classifier: Environment :: Plugins
Classifier: Intended Audience :: End Users/Desktop
Classifier: License :: OSI Approved :: BSD License
Classifier: Natural Language :: English
Classifier: Programming Language :: Python
Classifier: Programming Language :: Python :: 3
Classifier: Programming Language :: Python :: 3.10
Classifier: Programming Language :: Python :: 3.11
Classifier: Programming Language :: Python :: 3.12
Classifier: Programming Language :: Python :: 3.13
Classifier: Typing :: Typed
Requires-Dist: certifi
Requires-Dist: cryptography
Requires-Dist: idna
Requires-Dist: poetry (<2.1.0)
Requires-Dist: requests (==2.32.5)
Requires-Dist: urllib3
Project-URL: Bug Tracker, https://github.com/sbrunner/poetry-plugin-tweak-dependencies-version/issues
Project-URL: Repository, https://github.com/sbrunner/poetry-plugin-tweak-dependencies-version
